README.rst
setup.py
./GraphEM/QUIC.cpp
GraphEM/GraphEstimation.py
GraphEM/QUIC.py
GraphEM/__init__.py
GraphEM/graph.py
GraphEM/iridge.py
GraphEM/reconjob.py
GraphEM/solver.py
GraphEM.egg-info/PKG-INFO
GraphEM.egg-info/SOURCES.txt
GraphEM.egg-info/dependency_links.txt
GraphEM.egg-info/not-zip-safe
GraphEM.egg-info/requires.txt
GraphEM.egg-info/top_level.txt