Metadata-Version: 2.1
Name: GraphEM
Version: 0.1.6
Summary: Gaussian Markov random ﬁelds embedded within an EM algorithm
Home-page: https://github.com/fzhu2e/GraphEM
Author: Feng Zhu, Dominique Guillot, Julien Emile-Geay
Author-email: fengzhu@usc.edu, dguillot@udel.edu, julieneg@usc.edu
License: GPL-3.0 license
Keywords: GraphEM
Platform: UNKNOWN
Classifier: Natural Language :: English
Classifier: Programming Language :: Python :: 3.8
